setup.py
reqgithub/__init__.py
reqgithub/catalogo.py
reqgithub/github.py
reqgithub.egg-info/PKG-INFO
reqgithub.egg-info/SOURCES.txt
reqgithub.egg-info/dependency_links.txt
reqgithub.egg-info/not-zip-safe
reqgithub.egg-info/requires.txt
reqgithub.egg-info/top_level.txt