Metadata-Version: 1.1
Name: reqgithub
Version: 0.1
Summary: Test of pypi for PyPratico Cohort
Home-page: https://github.com/renzon/reqgithub
Author: Renzo Nuccitelli
Author-email: renzo.n@gmail.com
License: BSD
Platform: UNKNOWN
Classifier: Development Status :: 4 - Beta
Classifier: Environment :: Web Environment
Classifier: Intended Audience :: Developers
Classifier: License :: OSI Approved :: BSD License
Classifier: Operating System :: OS Independent
Classifier: Programming Language :: Python
Classifier: Framework :: Paste
